omamo/__init__.py
omamo/ic.py
omamo/inference.py
omamo/data/go_ic.dat
omamo-0.2.1.data/scripts/omamo
omamo-0.2.1.dist-info/METADATA
omamo-0.2.1.dist-info/WHEEL
omamo-0.2.1.dist-info/top_level.txt
omamo-0.2.1.dist-info/RECORD
