Metadata-Version: 2.1
Name: omamo
Version: 0.2.1
Summary: OMAmo - orthology-based model organism selection
Home-page: https://github.com/DessimozLab/omamo
Author: Alina Nicheperovich, Sina Majidian and Adrian Altenhoff
License: LGPLv3
Platform: UNKNOWN
Requires-Python: >=3.6
Requires-Dist: numpy
Requires-Dist: pandas
Requires-Dist: tables
Requires-Dist: pyoma
Requires-Dist: tqdm
Requires-Dist: importlib-resources ; python_version < "3.9"
